mimodulo_sc/__init__.py
mimodulo_sc-0.1.dist-info/METADATA
mimodulo_sc-0.1.dist-info/WHEEL
mimodulo_sc-0.1.dist-info/top_level.txt
mimodulo_sc-0.1.dist-info/RECORD
