Metadata-Version: 2.1
Name: mimodulo_sc
Version: 0.1
Summary: Un módulo simple para saludar
Home-page: https://tuurl.com
Author: Sebastián Cardona
Author-email: sebascarmun@gmail.com
Classifier: Programming Language :: Python :: 3
Classifier: License :: OSI Approved :: MIT License
Classifier: Operating System :: OS Independent
Requires-Python: >=3.6
